<collection xmlns="http://exist.sourceforge.net/NS/exist" name="/db/apps/eXide/resources/css/font-awesome/fonts" version="1" owner="eXide" group="eXide" mode="775" created="2018-08-25T13:15:31.395Z">
    <acl entries="0" version="1"/>
    <resource type="BinaryResource" name="fontawesome-webfont.ttf" skip="no" owner="eXide" group="eXide" mode="775" created="2018-08-25T13:15:31.457Z" modified="2018-08-25T13:15:31.457Z" filename="fontawesome-webfont.ttf" mimetype="application/octet-stream">
        <acl entries="0" version="1"/>
    </resource>
    <resource type="XMLResource" name="fontawesome-webfont.svg" skip="no" owner="eXide" group="eXide" mode="775" created="2018-08-25T13:15:31.401Z" modified="2018-08-25T13:15:31.401Z" filename="fontawesome-webfont.svg" mimetype="image/svg+xml">
        <acl entries="0" version="1"/>
    </resource>
    <resource type="BinaryResource" name="fontawesome-webfont.woff" skip="no" owner="eXide" group="eXide" mode="775" created="2018-08-25T13:15:31.4Z" modified="2018-08-25T13:15:31.4Z" filename="fontawesome-webfont.woff" mimetype="application/font-woff">
        <acl entries="0" version="1"/>
    </resource>
    <resource type="BinaryResource" name="fontawesome-webfont.eot" skip="no" owner="eXide" group="eXide" mode="775" created="2018-08-25T13:15:31.4Z" modified="2018-08-25T13:15:31.4Z" filename="fontawesome-webfont.eot" mimetype="application/octet-stream">
        <acl entries="0" version="1"/>
    </resource>
    <resource type="BinaryResource" name="FontAwesome.otf" skip="no" owner="eXide" group="eXide" mode="775" created="2018-08-25T13:15:31.396Z" modified="2018-08-25T13:15:31.396Z" filename="FontAwesome.otf" mimetype="application/octet-stream">
        <acl entries="0" version="1"/>
    </resource>
</collection>